hubspot_tech_writing/cli.py
hubspot_tech_writing/core.py
hubspot_tech_writing/html.py
hubspot_tech_writing/hubspot_api.py
hubspot_tech_writing-0.1.2.dist-info/licenses/LICENSE
hubspot_tech_writing-0.1.2.dist-info/METADATA
hubspot_tech_writing-0.1.2.dist-info/WHEEL
hubspot_tech_writing-0.1.2.dist-info/entry_points.txt
hubspot_tech_writing-0.1.2.dist-info/top_level.txt
hubspot_tech_writing-0.1.2.dist-info/RECORD
