Metadata-Version: 2.4
Name: hubspot-tech-writing
Version: 0.1.2
Summary: Support technical writing on HubSpot using Markdown.
Author-email: Andreas Motl <andreas.motl@crate.io>
License: Apache License 2.0
Project-URL: changelog, https://github.com/tech-writing/hubspot-tech-writing/blob/main/CHANGES.md
Project-URL: documentation, https://github.com/tech-writing/hubspot-tech-writing
Project-URL: homepage, https://github.com/tech-writing/hubspot-tech-writing
Project-URL: repository, https://github.com/tech-writing/hubspot-tech-writing
Keywords: html,hubspot,markdown,tech-writing
Classifier: Development Status :: 4 - Beta
Classifier: Environment :: Console
Classifier: Intended Audience :: Customer Service
Classifier: Intended Audience :: Developers
Classifier: Intended Audience :: Education
Classifier: Intended Audience :: Information Technology
Classifier: Intended Audience :: Telecommunications Industry
Classifier: License :: OSI Approved :: Apache Software License
Classifier: Operating System :: MacOS :: MacOS X
Classifier: Operating System :: POSIX :: Linux
Classifier: Operating System :: Unix
Classifier: Programming Language :: Python
Classifier: Programming Language :: Python :: 3 :: Only
Classifier: Programming Language :: Python :: 3.8
Classifier: Programming Language :: Python :: 3.9
Classifier: Programming Language :: Python :: 3.10
Classifier: Programming Language :: Python :: 3.11
Classifier: Programming Language :: Python :: 3.12
Classifier: Programming Language :: Python :: 3.13
Classifier: Programming Language :: Python :: 3.14
Classifier: Topic :: Communications
Classifier: Topic :: Education
Classifier: Topic :: Software Development :: Libraries
Classifier: Topic :: Text Processing
Classifier: Topic :: Text Processing :: Markup
Classifier: Topic :: Text Processing :: Markup :: HTML
Classifier: Topic :: Text Processing :: Markup :: Markdown
Classifier: Topic :: Utilities
Requires-Python: >=3.8
License-File: LICENSE
Requires-Dist: beautifulsoup4<5
Requires-Dist: click<9
Requires-Dist: click-aliases<2
Requires-Dist: colorlog<7
Requires-Dist: hubspot-api-client<13,>=12
Requires-Dist: markdown<4
Requires-Dist: mkdocs-linkcheck<2
Requires-Dist: requests<3
Requires-Dist: setuptools<81
Provides-Extra: develop
Requires-Dist: black<26; extra == "develop"
Requires-Dist: mypy<1.20; extra == "develop"
Requires-Dist: poethepoet<1; extra == "develop"
Requires-Dist: pyproject-fmt<3; extra == "develop"
Requires-Dist: ruff<0.15; extra == "develop"
Requires-Dist: validate-pyproject<1; extra == "develop"
Provides-Extra: release
Requires-Dist: build<2; extra == "release"
Requires-Dist: twine<7; extra == "release"
Provides-Extra: test
Requires-Dist: pytest<9; extra == "test"
Requires-Dist: pytest-cov<7; extra == "test"
Requires-Dist: pytest-mock<4; extra == "test"
Dynamic: license-file
